README.rst
setup.cfg
setup.py
miio/__init__.py
miio/cli.py
miio/miio.py
miio/protocol.py
miio/version.py
python2_miio.egg-info/PKG-INFO
python2_miio.egg-info/SOURCES.txt
python2_miio.egg-info/dependency_links.txt
python2_miio.egg-info/entry_points.txt
python2_miio.egg-info/requires.txt
python2_miio.egg-info/top_level.txt